<?xml version="1.0" encoding="utf-8"?>
<Trigger>
  <ClientName>Canada</ClientName>
  <AppName>Canada006</AppName>
  <RunDetail>
    <RunNumber>QJC_CND_006_00002O</RunNumber>
    <ComponentStatus>
      <Status>success</Status>
      <ComponentStartDate>03-10-2017 11:14:56</ComponentStartDate>
      <ComponentEndDate>03-10-2017 11:15:02</ComponentEndDate>
      <ErrorDescription></ErrorDescription>
    </ComponentStatus>
    <RunComponentStatusId>419</RunComponentStatusId>
  </RunDetail>
  <ComponentDetail>
    <ComponentName>UploadFile</ComponentName>
    <ComponentExe>E:\Jaspreet\AutomationNew\Automation\Component\Uploader\Uploader\bin\Debug\Uploader.exe</ComponentExe>
    <ComponentStatusDirectory>E:\Jaspreet\AutomationNew\Automation\Working\Trigger\Status</ComponentStatusDirectory>
    <ComponentInputLocation></ComponentInputLocation>
    <ComponentOutputLocation></ComponentOutputLocation>
    <ComponentConfigXmlFilePath></ComponentConfigXmlFilePath>
  </ComponentDetail>
</Trigger>